oebl_research_backend/__init__.py
oebl_research_backend/admin.py
oebl_research_backend/api_urls_v1.py
oebl_research_backend/api_views.py
oebl_research_backend/migrations/0001_initial.py
oebl_research_backend/migrations/__init__.py
oebl_research_backend/models.py
oebl_research_backend/serializers.py
oebl_research_backend/tasks.py
oebl_research_backend/urls.py
oebl_research_backend-0.1.4.dist-info/WHEEL
oebl_research_backend-0.1.4.dist-info/METADATA
oebl_research_backend-0.1.4.dist-info/RECORD
