Metadata-Version: 2.1
Name: oebl-research-backend
Version: 0.1.4
Summary: Backend for the GND backed research tool used in the ÖBL
License: MIT
Author: Matthias Schlögl
Author-email: m.schloegl@gmail.com
Requires-Python: >=3.6,<3.7
Classifier: License :: OSI Approved :: MIT License
Classifier: Programming Language :: Python :: 3
Classifier: Programming Language :: Python :: 3.6
Requires-Dist: apis-core (>=0.15.1,<0.16.0)
Requires-Dist: celery (>=5.0.5,<6.0.0)
Requires-Dist: django-celery-results (>=2.0.1,<3.0.0)
Requires-Dist: oebl-irs-workflow (>=0.1.4,<0.2.0)
